{
    "data":
    {
        "index": "105",
        "name": "Al-Fil",
        "verse": [
            {
                "text": " أَلَمْ تَرَ كَيْفَ فَعَلَ رَبُّكَ بِأَصْحَٰبِ ٱلْفِيلِ ",
                "number": "١",
                "verse": "1",
                "audioID": "v1",
                "url": "105001.mp3"
            },
            {
                "text": " أَلَمْ يَجْعَلْ كَيْدَهُمْ فِى تَضْلِيلٍۢ ",
                "number": "٢",
                "verse": "2",
                "audioID": "v2",
                "url": "105002.mp3"
            },
            {
                "text": " وَأَرْسَلَ عَلَيْهِمْ طَيْرًا أَبَابِيلَ ",
                "number": "٣",
                "verse": "3",
                "audioID": "v3",
                "url": "105003.mp3"
            },
            {
                "text": " تَرْمِيهِم بِحِجَارَةٍۢ مِّن سِجِّيلٍۢ ",
                "number": "٤",
                "verse": "4",
                "audioID": "v4",
                "url": "105004.mp3"
            },
            {
                "text": " فَجَعَلَهُمْ كَعَصْفٍۢ مَّأْكُولٍۭ ",
                "number": "٥",
                "verse": "5",
                "audioID": "v5",
                "url": "105005.mp3"
            }

        ],
        "count": 5,
        "juz": [
            {
                "index": "30",
                "verse": {
                    "start": "1",
                    "end": "5"
                }
            }
        ]
    }
}